{
  "authorDailyContributionsMap": {
    "JustinChia1997": [
      {
        "insertions": 177,
        "deletions": 95,
        "date": "2019-10-02",
        "commitResults": [
          {
            "hash": "c39db3ff8270fc538901ceb0945529af78ff3403",
            "messageTitle": "Fixed all checkstyle errors on all packages",
            "messageBody": "",
            "insertions": 173,
            "deletions": 92
          },
          {
            "hash": "e28e715ac62e2b8947784b1dcfbc4d7d82adab0a",
            "messageTitle": "Fixed test case",
            "messageBody": "",
            "insertions": 2,
            "deletions": 2
          },
          {
            "hash": "5f569edb5a6357d980cf207d4fe2e524b73a67fb",
            "messageTitle": "Fixed test case part two",
            "messageBody": "",
            "insertions": 2,
            "deletions": 1
          }
        ]
      },
      {
        "insertions": 125,
        "deletions": 1,
        "date": "2019-10-09",
        "commitResults": [
          {
            "hash": "05ffeb70f906cc09108a164a72c2c2bc0d792606",
            "messageTitle": "Wrote Sample test Case",
            "messageBody": "",
            "insertions": 28,
            "deletions": 0
          },
          {
            "hash": "6fcb5bb931ef719c5e20a9962eb629e0d8911d5d",
            "messageTitle": "Added additional test for tasks",
            "messageBody": "",
            "insertions": 73,
            "deletions": 1
          },
          {
            "hash": "d671fbc974e2cb8dc04125e1d3196d6db80622d4",
            "messageTitle": "Added more testing",
            "messageBody": "",
            "insertions": 24,
            "deletions": 0
          }
        ]
      },
      {
        "insertions": 4,
        "deletions": 4,
        "date": "2019-10-16",
        "commitResults": [
          {
            "hash": "fdf3933d1f77487d5eea9673dac74fdf010416b7",
            "messageTitle": "fixed some tests",
            "messageBody": "",
            "insertions": 4,
            "deletions": 4
          }
        ]
      }
    ],
    "chenyuheng": [
      {
        "insertions": 21,
        "deletions": 26,
        "date": "2019-10-02",
        "commitResults": [
          {
            "hash": "a7651d1d66b557f7c5478896a697b74ba7585a20",
            "messageTitle": "fixed some javadoc related error",
            "messageBody": "",
            "insertions": 21,
            "deletions": 26
          }
        ]
      },
      {
        "insertions": 158,
        "deletions": 58,
        "date": "2019-10-09",
        "commitResults": [
          {
            "hash": "df75d6259cfa4f615a41ec1c40b651d4c937c593",
            "messageTitle": "added command typo correction",
            "messageBody": "",
            "insertions": 111,
            "deletions": 0
          },
          {
            "hash": "b9215e10431b72ef09f20e9c56abd6f08dab1336",
            "messageTitle": "clear up",
            "messageBody": "",
            "insertions": 47,
            "deletions": 58
          }
        ]
      }
    ],
    "jasonchanwq": [
      {
        "insertions": 76,
        "deletions": 19,
        "date": "2019-10-15",
        "commitResults": [
          {
            "hash": "00fefb3721badba4f0245c00c62e6740129983f5",
            "messageTitle": "Add link",
            "messageBody": "",
            "insertions": 59,
            "deletions": 15
          },
          {
            "hash": "cf4ca5760d2d069be1c236fb7b7b9063e74c0700",
            "messageTitle": "Pass checkstyle",
            "messageBody": "",
            "insertions": 17,
            "deletions": 4
          }
        ]
      },
      {
        "insertions": 110,
        "deletions": 5,
        "date": "2019-10-22",
        "commitResults": [
          {
            "hash": "7c4e73fed2d13c8ea2dcdb8def255ae03636cb76",
            "messageTitle": "Add Unlink and Remove",
            "messageBody": "",
            "insertions": 110,
            "deletions": 5
          }
        ]
      }
    ],
    "AugGust": [
      {
        "insertions": 21,
        "deletions": 2,
        "date": "2019-10-02",
        "commitResults": [
          {
            "hash": "6687ad806d63a776557b4d92246019038069bcd5",
            "messageTitle": "Fixed and added Javadocs for ViewScheCommand",
            "messageBody": "",
            "insertions": 21,
            "deletions": 2
          }
        ]
      },
      {
        "insertions": 29,
        "deletions": 6,
        "date": "2019-10-09",
        "commitResults": [
          {
            "hash": "71e7996a9662513d0a085621c299b2dba1ae2777",
            "messageTitle": "Added blank main window",
            "messageBody": "",
            "insertions": 18,
            "deletions": 0
          },
          {
            "hash": "22cd84b20516e485a31e29768bf9db065720a7d8",
            "messageTitle": "Fixed checkStyle errors",
            "messageBody": "",
            "insertions": 9,
            "deletions": 4
          },
          {
            "hash": "1357835232bb75a980079123e45b409a41c75686",
            "messageTitle": "Fixed javadoc formatting for Travis",
            "messageBody": "",
            "insertions": 2,
            "deletions": 2
          }
        ]
      },
      {
        "insertions": 89,
        "deletions": 73,
        "date": "2019-10-16",
        "commitResults": [
          {
            "hash": "c957b44ae279bcdb850b86ac7165ce7976be96f5",
            "messageTitle": "Linked initial output text Area and fixed some file names",
            "messageBody": "",
            "insertions": 78,
            "deletions": 13
          },
          {
            "hash": "4a53990391b9155e389871b208758ec08303091c",
            "messageTitle": "Attempt fix for making IntelliJ Form editor with Gradle",
            "messageBody": "",
            "insertions": 0,
            "deletions": 54
          },
          {
            "hash": "ab62aa4103ead1f7f5565aee8e1ed11994c3ba44",
            "messageTitle": "Fixed styles",
            "messageBody": "",
            "insertions": 7,
            "deletions": 5
          },
          {
            "hash": "43a4bdb907d01c484f67548d8b6de331a58de8f4",
            "messageTitle": "Fix checkstyles again",
            "messageBody": "",
            "insertions": 4,
            "deletions": 1
          }
        ]
      },
      {
        "insertions": 242,
        "deletions": 141,
        "date": "2019-10-21",
        "commitResults": [
          {
            "hash": "aa040f1d914c63ba44c5a97662f654f3cbd36787",
            "messageTitle": "Recreated Window using Eclipse Made Window accept inputs",
            "messageBody": "",
            "insertions": 131,
            "deletions": 31
          },
          {
            "hash": "888adb6e354101869768af12d4f03aa0af95262f",
            "messageTitle": "Fixed style errors",
            "messageBody": "",
            "insertions": 97,
            "deletions": 97
          },
          {
            "hash": "b18e1d75189bac7f2ec42c9c04a9d2bc23fee59c",
            "messageTitle": "Fixed styles again",
            "messageBody": "",
            "insertions": 9,
            "deletions": 8
          },
          {
            "hash": "b09c02a494e88c7dd22ea2a2e334d36266c2ba04",
            "messageTitle": "Fixed style reback for some reason",
            "messageBody": "",
            "insertions": 5,
            "deletions": 5
          }
        ]
      },
      {
        "insertions": 440,
        "deletions": 140,
        "date": "2019-10-22",
        "commitResults": [
          {
            "hash": "3a137b8a9b58b6ceba0f86057f5d314906ec5f59",
            "messageTitle": "Added percentage completed display",
            "messageBody": "",
            "insertions": 58,
            "deletions": 4
          },
          {
            "hash": "3b8346f3466f1c9123d0fed34476ab7f2edfbf15",
            "messageTitle": "Made percentage update live",
            "messageBody": "",
            "insertions": 12,
            "deletions": 4
          },
          {
            "hash": "0fa93e4a90b73c714e88cf73a2a025dee118ae69",
            "messageTitle": "Fixed checkmark and crosses in GUI",
            "messageBody": "",
            "insertions": 2,
            "deletions": 2
          },
          {
            "hash": "5c06de67a1e431c7ba041f8238772a1488a94939",
            "messageTitle": "Added Comments",
            "messageBody": "",
            "insertions": 5,
            "deletions": 2
          },
          {
            "hash": "452e0f8a71116d0fd8266c4deba01c27a2a2f4e5",
            "messageTitle": "Added and fixed more formatting and comments",
            "messageBody": "",
            "insertions": 39,
            "deletions": 28
          },
          {
            "hash": "637823c13e2825ed5fb93430a7d35e98c5ecb3a4",
            "messageTitle": "Fixed indentations",
            "messageBody": "",
            "insertions": 15,
            "deletions": 14
          },
          {
            "hash": "bccbf9a6ca2b7301cb04f46327c7a07954e10e1d",
            "messageTitle": "Fixed test character check",
            "messageBody": "",
            "insertions": 1,
            "deletions": 1
          },
          {
            "hash": "61a5034154558e5677ffceae5c159bab89a11735",
            "messageTitle": "Added pie chart progress display and help command Editted on startup message",
            "messageBody": "",
            "insertions": 105,
            "deletions": 9
          },
          {
            "hash": "85688fa6b7a8b70ad2a6e64f76a49bd7f8d138b8",
            "messageTitle": "Updated pie chart live",
            "messageBody": "",
            "insertions": 8,
            "deletions": 1
          },
          {
            "hash": "fcc9d9d12105bb005f7f5e164eae1074b2810658",
            "messageTitle": "Added input field history control Use up and down arrows to go through history",
            "messageBody": "",
            "insertions": 125,
            "deletions": 24
          },
          {
            "hash": "a5c22e6672dbb9f3d7a3d89d03b4c884c47541f6",
            "messageTitle": "Formatted and added Javadocs for PieChart",
            "messageBody": "",
            "insertions": 39,
            "deletions": 25
          },
          {
            "hash": "b183b7bc6e15c198ad9b3f155e90d5bfba87d545",
            "messageTitle": "Fixed style errors",
            "messageBody": "",
            "insertions": 27,
            "deletions": 23
          },
          {
            "hash": "33118fe80606f4172a4f4c09de7771b951a6ab6f",
            "messageTitle": "Attempt to fix style error",
            "messageBody": "",
            "insertions": 2,
            "deletions": 1
          },
          {
            "hash": "b23b769f359453c80c8cd4439646958f35676caf",
            "messageTitle": "Attempt fix style again",
            "messageBody": "",
            "insertions": 2,
            "deletions": 2
          }
        ]
      },
      {
        "insertions": 12,
        "deletions": 4,
        "date": "2019-10-23",
        "commitResults": [
          {
            "hash": "8024047036e1e162025d93c68ce55f7c01d01865",
            "messageTitle": "Fixed style at last",
            "messageBody": "",
            "insertions": 1,
            "deletions": 1
          },
          {
            "hash": "55e2ce377393e9e1855e41600c26ff73ef84dd92",
            "messageTitle": "Small GUI change and first attempt at JAR",
            "messageBody": "",
            "insertions": 1,
            "deletions": 1
          },
          {
            "hash": "261914f56b53d5707610b16686a033a96d6727e2",
            "messageTitle": "Made Storage generate missing folders/files. Packaged a working version of duke pro JAR",
            "messageBody": "",
            "insertions": 10,
            "deletions": 2
          }
        ]
      }
    ],
    "yuyanglin28": [
      {
        "insertions": 100,
        "deletions": 39,
        "date": "2019-10-09",
        "commitResults": [
          {
            "hash": "57921bae33d83537433285c813981b9d7fb107a5",
            "messageTitle": "test class for period and last task",
            "messageBody": "",
            "insertions": 90,
            "deletions": 0
          },
          {
            "hash": "a2a608bbecfbe8f1fde29f8a4f2982baf6984253",
            "messageTitle": "fix check style",
            "messageBody": "",
            "insertions": 8,
            "deletions": 19
          },
          {
            "hash": "4a7d9e9771b67fab3d9c9c10df08dc6c03be9906",
            "messageTitle": "fix check style",
            "messageBody": "",
            "insertions": 1,
            "deletions": 1
          },
          {
            "hash": "a9cb17184d6f089d911f03522b982b753c5f10ec",
            "messageTitle": "fix error",
            "messageBody": "",
            "insertions": 1,
            "deletions": 19
          }
        ]
      },
      {
        "insertions": 263,
        "deletions": 36,
        "date": "2019-10-15",
        "commitResults": [
          {
            "hash": "2776fa7013216565f7a72ffd406adcea66ffdb3c",
            "messageTitle": "add member \u0026 show member list",
            "messageBody": "",
            "insertions": 263,
            "deletions": 36
          }
        ]
      }
    ]
  },
  "authorFinalContributionMap": {
    "JustinChia1997": 246,
    "chenyuheng": 179,
    "jasonchanwq": 177,
    "AugGust": 493,
    "yuyanglin28": 328
  },
  "authorFileTypeContributionMap": {
    "JustinChia1997": {
      "tests": 125,
      "functional": 121
    },
    "chenyuheng": {
      "tests": 46,
      "functional": 133
    },
    "jasonchanwq": {
      "tests": 0,
      "functional": 177
    },
    "AugGust": {
      "tests": 1,
      "functional": 492
    },
    "yuyanglin28": {
      "tests": 52,
      "functional": 276
    }
  },
  "authorContributionVariance": {
    "JustinChia1997": 2573.6064,
    "chenyuheng": 1417.2413,
    "jasonchanwq": 633.7466,
    "AugGust": 14175.132,
    "yuyanglin28": 3118.4404
  },
  "authorDisplayNameMap": {
    "JustinChia1997": "CS2113-T14-4 JUS  . . JIN",
    "chenyuheng": "CS2113-T14-4 CHE  . . ENG",
    "jasonchanwq": "CS2113-T14-4 CHA  . . SON",
    "AugGust": "CS2113-T14-4 LIM  . . ING",
    "yuyanglin28": "CS2113-T14-4 LIN  . . ANG"
  }
}
