{
  "authorDailyContributionsMap": {
    "Lim Ting Wei": [],
    "e0318465": [],
    "Dou-Maokang": [
      {
        "insertions": 335,
        "deletions": 40,
        "date": "2019-10-02",
        "commitResults": [
          {
            "hash": "ccd98a34cd62f4e8504c567fd5d9282351b40ed0",
            "messageTitle": "added variable priority, method setPriority() and getPriority in Task; added new command SetPriorityCommand",
            "messageBody": "",
            "insertions": 25,
            "deletions": 0
          },
          {
            "hash": "3ad91c370e6bb1b2ef05a00fc6645e28e9cbbce3",
            "messageTitle": "added PriorityStorage for storing priority of every task",
            "messageBody": "",
            "insertions": 45,
            "deletions": 0
          },
          {
            "hash": "23e9b80333599ce99b9a3b7aff459d18f711eb16",
            "messageTitle": "updated Duke to enable loading PriorityList",
            "messageBody": "",
            "insertions": 22,
            "deletions": 3
          },
          {
            "hash": "a186ff877b726b2711d31df65db4d52bb3adaa36",
            "messageTitle": "updated Duke",
            "messageBody": "",
            "insertions": 2,
            "deletions": 2
          },
          {
            "hash": "eaec9bbe30374efa024040044264082d7d2ef7a9",
            "messageTitle": "implemented PriorityList for adding priority for each task; updated Duke to accommodate PriorityList",
            "messageBody": "",
            "insertions": 72,
            "deletions": 14
          },
          {
            "hash": "123d32165caa231a72d622aeaf8affe57523f84d",
            "messageTitle": "updated PriorityList",
            "messageBody": "",
            "insertions": 24,
            "deletions": 9
          },
          {
            "hash": "4a4ad994101b5172abff5d3d17536266cdcf58e6",
            "messageTitle": "updated Ui to show list of tasks with priorities",
            "messageBody": "",
            "insertions": 14,
            "deletions": 0
          },
          {
            "hash": "858d92ba39310deb01f24edbd2d7de2256f64d5d",
            "messageTitle": "updated Parser to include ListPriorityCommand",
            "messageBody": "",
            "insertions": 2,
            "deletions": 0
          },
          {
            "hash": "225131e555e9fea6435ac7d86d1a624214c5fc40",
            "messageTitle": "updated Command and Ui to accommodate new ListPriorityCommand",
            "messageBody": "",
            "insertions": 79,
            "deletions": 4
          },
          {
            "hash": "7c1f2078090929fc114137ac63220c59a9521abc",
            "messageTitle": "updated Ui",
            "messageBody": "",
            "insertions": 3,
            "deletions": 2
          },
          {
            "hash": "4d235402d8dfb18ee573755f5797f2a6995a5e10",
            "messageTitle": "added javadoc for PriorityStorage",
            "messageBody": "",
            "insertions": 6,
            "deletions": 1
          },
          {
            "hash": "6901e5b3f19ca89aab0a9f77e2f4c0e18dbd1c53",
            "messageTitle": "added javadoc for PriorityList",
            "messageBody": "",
            "insertions": 40,
            "deletions": 5
          },
          {
            "hash": "c6334cf3048deee457678aebe0f9563e53cf9020",
            "messageTitle": "updated javadoc for ListPriorityCommand",
            "messageBody": "",
            "insertions": 1,
            "deletions": 0
          }
        ]
      }
    ],
    "Ong Yu Xuan (Maxx)": [
      {
        "insertions": 7,
        "deletions": 302,
        "date": "2019-10-02",
        "commitResults": [
          {
            "hash": "5cbb2ac278f3f4f8e78612344234d46e21abc41b",
            "messageTitle": "Revert \"updated aboutUs image\" (#88)",
            "messageBody": "",
            "insertions": 7,
            "deletions": 302
          }
        ]
      }
    ],
    "Aw Rui Huan": [],
    "talesrune": [
      {
        "insertions": 336,
        "deletions": 17,
        "date": "2019-09-29",
        "commitResults": [
          {
            "hash": "50387071fd8379be8c21732d6559ffa9153196e5",
            "messageTitle": "Implemented C-Update.",
            "messageBody": "",
            "insertions": 336,
            "deletions": 17
          }
        ]
      }
    ]
  },
  "authorFinalContributionMap": {
    "Lim Ting Wei": 0,
    "e0318465": 0,
    "Dou-Maokang": 0,
    "Ong Yu Xuan (Maxx)": 0,
    "Aw Rui Huan": 0,
    "talesrune": 336
  },
  "authorFileTypeContributionMap": {
    "Lim Ting Wei": {
      "java": 0,
      "gradle": 0,
      "css": 0,
      "fxml": 0
    },
    "e0318465": {
      "java": 0,
      "gradle": 0,
      "css": 0,
      "fxml": 0
    },
    "Dou-Maokang": {
      "java": 0,
      "gradle": 0,
      "css": 0,
      "fxml": 0
    },
    "Ong Yu Xuan (Maxx)": {
      "java": 0,
      "gradle": 0,
      "css": 0,
      "fxml": 0
    },
    "Aw Rui Huan": {
      "java": 0,
      "gradle": 0,
      "css": 0,
      "fxml": 0
    },
    "talesrune": {
      "java": 336,
      "gradle": 0,
      "css": 0,
      "fxml": 0
    }
  },
  "authorContributionVariance": {
    "Lim Ting Wei": 0.0,
    "e0318465": 0.0,
    "Dou-Maokang": 22500.0,
    "Ong Yu Xuan (Maxx)": 15276.959,
    "Aw Rui Huan": 0.0,
    "talesrune": 19937.44
  },
  "authorDisplayNameMap": {
    "Lim Ting Wei": "Lim Ting Wei",
    "e0318465": "e0318465",
    "Dou-Maokang": "Dou-Maokang",
    "Ong Yu Xuan (Maxx)": "Ong Yu Xuan (Maxx)",
    "Aw Rui Huan": "Aw Rui Huan",
    "talesrune": "talesrune"
  }
}
